clstr.py
setup.py
clstr.egg-info/PKG-INFO
clstr.egg-info/SOURCES.txt
clstr.egg-info/dependency_links.txt
clstr.egg-info/entry_points.txt
clstr.egg-info/top_level.txt