Metadata-Version: 1.0
Name: clstr
Version: 0.1.0
Summary: A quick'n'dirty cluster manager for quick'n'dirty clusters.
Home-page: https://github.com/mossblaser/clstr
Author: Jonathan Heathcote
Author-email: mail@jhnet.co.uk
License: GPLv2
Platform: UNKNOWN
